qtxdbpackage/__init__.py
qtxdbpackages-1.0.dist-info/METADATA
qtxdbpackages-1.0.dist-info/WHEEL
qtxdbpackages-1.0.dist-info/top_level.txt
qtxdbpackages-1.0.dist-info/RECORD
